binstore.cp38-win_amd64.pyd
binstore-1.7.2.dist-info/LICENSE
binstore-1.7.2.dist-info/METADATA
binstore-1.7.2.dist-info/WHEEL
binstore-1.7.2.dist-info/top_level.txt
binstore-1.7.2.dist-info/RECORD
