Metadata-Version: 2.1
Name: binstore
Version: 1.7.2
Summary: Module to implement C extension Bins class for bin-based storage of items
Home-page: https://pypi.org/project/binstore/
Author: John Herrema
Author-email: jherrema@gmail.com
License: UNKNOWN
Platform: UNKNOWN
Classifier: Programming Language :: Python :: 3
Classifier: License :: OSI Approved :: MIT License
Classifier: Operating System :: OS Independent
Requires-Python: >=3.6
